sentimentscopeai/__init__.py
sentimentscopeai/core.py
sentimentscopeai-1.4.1.dist-info/licenses/LICENSE
sentimentscopeai-1.4.1.dist-info/METADATA
sentimentscopeai-1.4.1.dist-info/WHEEL
sentimentscopeai-1.4.1.dist-info/top_level.txt
sentimentscopeai-1.4.1.dist-info/RECORD
