Metadata-Version: 2.4
Name: sentimentscopeai
Version: 1.4.1
Summary: Transformer-based review sentiment analysis and actionable insight generation.
Author: Vignesh Thondikulam
License: MIT
Project-URL: Homepage, https://github.com/VigneshT24/SentimentScopeAI
Project-URL: Repository, https://github.com/VigneshT24/SentimentScopeAI
Requires-Python: >=3.9
License-File: LICENSE
Requires-Dist: torch
Requires-Dist: transformers
Requires-Dist: sentencepiece
Requires-Dist: playwright>=1.40.0
Requires-Dist: playwright-stealth>=0.1.0
Requires-Dist: seleniumbase>=4.0.0
Dynamic: license-file
